MANIFEST.in
README.rst
auto_exec
openstack_userparams.conf
requirements.txt
setup.py
collectds/__init__.py
collectds/base.py
collectds/ceph_osd_stats.py
collectds/ceph_pg_mon_status.py
collectds/ceph_pool_osd.py
collectds/check_openstack_api.py
collectds/dbi.py
collectds/haproxy.py
collectds/hypervisor_stats.py
collectds/mysql.py
collectds/openstack.py
collectds/openstack_cinder.py
collectds/openstack_glance.py
collectds/openstack_keystone.py
collectds/openstack_neutron.py
collectds/openstack_nova.py
collectds/pacemaker_resource.py
collectds/rabbitmq_info.py
collectds.egg-info/PKG-INFO
collectds.egg-info/SOURCES.txt
collectds.egg-info/dependency_links.txt
collectds.egg-info/requires.txt
collectds.egg-info/top_level.txt