Metadata-Version: 1.1
Name: collectds
Version: 0.1.1
Summary: This module references Fuel-LMA and is modified to collect OpenStack service running status.
Home-page: UNKNOWN
Author: You-Ming-Yang
Author-email: ymyscugs@gmail.com
License: LICENSE
Platform: linux
Classifier: Development Status :: 3 - Alpha
Classifier: Environment :: OpenStack
Classifier: Intended Audience :: Developers
Classifier: License :: OSI Approved :: Apache Software License
Classifier: Programming Language :: Python :: 2.7
